bitty/__init__.py
bitty/chunking.py
bitty/py.typed
bitty/train.py
bitty_tokenizer-0.1.5.dist-info/METADATA
bitty_tokenizer-0.1.5.dist-info/WHEEL
bitty_tokenizer-0.1.5.dist-info/entry_points.txt
bitty_tokenizer-0.1.5.dist-info/top_level.txt
bitty_tokenizer-0.1.5.dist-info/RECORD
