Metadata-Version: 2.4
Name: bitty-tokenizer
Version: 0.1.5
Summary: A bitty BPE tokenizer library
Author-email: Mohit <28mohit2002dulani@gmail.com>
Requires-Python: >=3.10
